[
  {
    "toolmode": "chopping",
    "ingredients":
    [ 
      {"inputs": 
       [
         {"type": "block", "code": "floralzonesmediterraneanregion:log-placed-*-ud", "name": "wood", "loadFromProperties": "floralzonesmediterraneanregion:block/wood"}
       ]
      }
    ],
    "output": {"type": "block", "code": "floralzonesmediterraneanregion:logslab-{wood}-barked-north-free", "quantity": 2}
  },
  {
    "toolmode": "chopping",
    "ingredients":
    [ 
      {"inputs": 
       [
         {"type": "block", "code": "floralzonesmediterraneanregion:debarkedlog-*-ud", "name": "wood", "loadFromProperties": "floralzonesmediterraneanregion:block/wood"}
       ]
      }
    ],
    "output": {"type": "block", "code": "floralzonesmediterraneanregion:logslab-{wood}-debarked-north-free", "quantity": 2}
  }
]